freetubedb/__init__.py
freetubedb/parser.py
freetubedb/models/__init__.py
freetubedb/models/freetube_playlist.py
freetubedb/models/freetube_video.py
freetubedb-1.0.1.dist-info/METADATA
freetubedb-1.0.1.dist-info/WHEEL
freetubedb-1.0.1.dist-info/licenses/LICENSE
freetubedb-1.0.1.dist-info/RECORD
