Metadata-Version: 2.4
Name: freetubedb
Version: 1.0.1
Summary: Python library for interacting with FreeTube's playlists.db file
Project-URL: Documentation, https://github.com/FawkesOficial/python-freetubedb#readme
Project-URL: Issues, https://github.com/FawkesOficial/python-freetubedb/issues
Project-URL: Source, https://github.com/FawkesOficial/python-freetubedb
Author-email: Mário Lourenço <mario.s.lourenco@protonmail.com>
License-Expression: GPL-3.0
License-File: LICENSE
Classifier: Development Status :: 4 - Beta
Classifier: Programming Language :: Python
Classifier: Programming Language :: Python :: 3.10
Classifier: Programming Language :: Python :: 3.11
Classifier: Programming Language :: Python :: 3.12
Classifier: Programming Language :: Python :: Implementation :: CPython
Classifier: Programming Language :: Python :: Implementation :: PyPy
Requires-Python: >=3.10
